pyadconnector/__init__.py
pyadconnector/connectors.py
pyadconnector/enums.py
pyadconnector/exceptions.py
pyadconnector/models.py
pyadconnector/settings.py
pyadconnector/utils.py
pyadconnector-0.2.1.dist-info/METADATA
pyadconnector-0.2.1.dist-info/WHEEL
pyadconnector-0.2.1.dist-info/RECORD
