Metadata-Version: 2.1
Name: pyadconnector
Version: 0.2.1
Summary: 
Author: Simone Dalla
Author-email: simodalla@gmail.com
Requires-Python: >=3.11,<4.0
Classifier: Programming Language :: Python :: 3
Classifier: Programming Language :: Python :: 3.11
Requires-Dist: pydantic-settings-toml (>=0.2.0,<0.3.0)
Requires-Dist: pydantic[email] (>=2.4.2,<3.0.0)
Requires-Dist: pynteracta (>=0.4.1,<0.5.0)
Requires-Dist: python-ldap (>=3.4.3,<4.0.0)
Requires-Dist: pytz (>=2023.3,<2024.0)
